{"about.md":"67558f22","dev_roadmap.md":"59bac4c2","development_docs_dev_docs.md":"1c7099a1","development_docs_pages.md":"e3ea318f","development_docs_standards.md":"c022dc66","firmware_guide_configure_firmware.md":"ad3a7a27","firmware_guide_environments.md":"35702a84","firmware_guide_firmware.md":"3ff987da","firmware_guide_mdns.md":"f7cf7152","firmware_guide_rest_api.md":"c031cbdb","firmware_guide_setup_vscode.md":"5c098e1b","firmware_guide_update_platformio.md":"f77a6333","firmware_guide_upload_and_update_firmware.md":"6b6412b0","getting_started_intro.md":"66aa4f59","getting_started_things_to_know.md":"36842c3c","how_to_build_creating_your_own_mount.md":"ac844386","contact.md":"2a8274c7","how_to_build_parts_list.md":"a0e01995","index.md":"c15589ce","misc_faq.md":"557dde35","misc_vrc_avatar_setup.md":"ffcc0d92","software_guide_eyetrackvr_app_guide.md":"139d2041","software_guide_build_software.md":"a667b707","how_to_build_full_build.md":"955d0e98","archive_fox_ir_v2_build_instructions.md":"818f52c9"}
